guirecognizer/__init__.py
guirecognizer/action_type.py
guirecognizer/common.py
guirecognizer/mouse_helper.py
guirecognizer/preprocessing.py
guirecognizer/preprocessing_type.py
guirecognizer/recognizer.py
guirecognizer/types.py
guirecognizer-0.1.1.dist-info/licenses/LICENSE
guirecognizer-0.1.1.dist-info/METADATA
guirecognizer-0.1.1.dist-info/WHEEL
guirecognizer-0.1.1.dist-info/top_level.txt
guirecognizer-0.1.1.dist-info/RECORD
