Metadata-Version: 2.4
Name: guirecognizer
Version: 0.1.1
Summary: Recognize on-screen patterns and perform GUI interactions
Author-email: FAB V <fab5code@gmail.com>
License-Expression: MIT
Project-URL: Repository, https://github.com/fab5code/guirecognizer.git
Project-URL: Issues, https://github.com/fab5code/guirecognizer/issues
Keywords: GUI,recognize,screen
Classifier: Development Status :: 3 - Alpha
Classifier: Intended Audience :: Developers
Classifier: Programming Language :: Python :: 3.13
Requires-Python: >=3.13
License-File: LICENSE
Requires-Dist: numpy
Requires-Dist: opencv-python
Requires-Dist: imagehash
Requires-Dist: pyautogui
Provides-Extra: dev
Requires-Dist: packaging; extra == "dev"
Requires-Dist: coverage; extra == "dev"
Requires-Dist: build; extra == "dev"
Requires-Dist: twine; extra == "dev"
Requires-Dist: pytesseract; extra == "dev"
Requires-Dist: easyocr; extra == "dev"
Requires-Dist: sphinx; extra == "dev"
Requires-Dist: sphinx_rtd_theme; extra == "dev"
Requires-Dist: sphinx-autodoc-typehints; extra == "dev"
Dynamic: license-file
